greenheart/__init__.py
greenheart/simulation/__init__.py
greenheart/simulation/greenheart_simulation.py
greenheart/simulation/technologies/__init__.py
greenheart/simulation/technologies/ammonia/__init__.py
greenheart/simulation/technologies/ammonia/ammonia.py
greenheart/simulation/technologies/hydrogen/__init__.py
greenheart/simulation/technologies/hydrogen/desal/__init__.py
greenheart/simulation/technologies/hydrogen/desal/desal_model.py
greenheart/simulation/technologies/hydrogen/desal/desal_model_eco.py
greenheart/simulation/technologies/hydrogen/electrolysis/H2_cost_model.py
greenheart/simulation/technologies/hydrogen/electrolysis/PEM_H2_LT_electrolyzer.py
greenheart/simulation/technologies/hydrogen/electrolysis/PEM_H2_LT_electrolyzer_Clusters.py
greenheart/simulation/technologies/hydrogen/electrolysis/PEM_costs_Singlitico_model.py
greenheart/simulation/technologies/hydrogen/electrolysis/PEM_electrolyzer_IVcurve.py
greenheart/simulation/technologies/hydrogen/electrolysis/PEM_tools.py
greenheart/simulation/technologies/hydrogen/electrolysis/__init__.py
greenheart/simulation/technologies/hydrogen/electrolysis/optimization_utils_linear.py
greenheart/simulation/technologies/hydrogen/electrolysis/pem_mass_and_footprint.py
greenheart/simulation/technologies/hydrogen/electrolysis/run_PEM_master.py
greenheart/simulation/technologies/hydrogen/electrolysis/run_h2_PEM.py
greenheart/simulation/technologies/hydrogen/electrolysis/run_h2_PEM_eco.py
greenheart/simulation/technologies/hydrogen/electrolysis/run_h2_clusters.py
greenheart/simulation/technologies/hydrogen/electrolysis/test_opt.ipynb
greenheart/simulation/technologies/hydrogen/electrolysis/PEM_BOP/BOP_efficiency_BOL.csv
greenheart/simulation/technologies/hydrogen/electrolysis/PEM_BOP/PEM_BOP.py
greenheart/simulation/technologies/hydrogen/electrolysis/PEM_BOP/README.md
greenheart/simulation/technologies/hydrogen/h2_storage/Bulk Hydrogen Cost as Function of Capacity.docx
greenheart-0.1.4.dist-info/LICENSE
greenheart-0.1.4.dist-info/METADATA
greenheart-0.1.4.dist-info/WHEEL
greenheart-0.1.4.dist-info/top_level.txt
greenheart-0.1.4.dist-info/RECORD
