Metadata-Version: 2.2
Name: greenheart
Version: 0.1.4
Summary: Green Hydrogen Energy and Renewable Technologies
Author-email: NREL <dguittet@nrel.gov>
License: **Note: The ProFAST model is distributed with GreenHEART but operates under a separate license agreement. Users must agree to the license terms of ProFAST located at `ProFAST/InternalUseTermsForDownloadableSoftware-ProFAST.docx`.**
Project-URL: source, https://github.com/NREL/GreenHEART
Project-URL: issues, https://github.com/NREL/GreenHEART/issues
Project-URL: changelog, https://github.com/NREL/GreenHEART/blob/main/CHANGELOG.md
Keywords: python3,hybrid-energy,wind-energy,solar-energy,layout-optimization
Classifier: Development Status :: 4 - Beta
Classifier: Intended Audience :: Developers
Classifier: Intended Audience :: Science/Research
Classifier: Intended Audience :: Other Audience
Classifier: License :: OSI Approved :: BSD License
Classifier: Natural Language :: English
Classifier: Operating System :: OS Independent
Classifier: Programming Language :: Python
Classifier: Programming Language :: Python :: 3 :: Only
Classifier: Programming Language :: Python :: 3.9
Classifier: Programming Language :: Python :: 3.10
Classifier: Programming Language :: Python :: 3.11
Classifier: Topic :: Scientific/Engineering
Classifier: Topic :: Software Development :: Libraries :: Python Modules
Requires-Python: <3.12,>=3.9
License-File: LICENSE
Requires-Dist: Cython
Requires-Dist: NREL-PySAM==4.2.0
Requires-Dist: Pillow
Requires-Dist: Plotly
Requires-Dist: Pyomo>=6.1.2
Requires-Dist: fastkml
Requires-Dist: floris
Requires-Dist: future
Requires-Dist: global_land_mask
Requires-Dist: hybridbosse
Requires-Dist: lcoe
Requires-Dist: lxml
Requires-Dist: matplotlib
Requires-Dist: multiprocessing-on-dill
Requires-Dist: numpy
Requires-Dist: numpy-financial
Requires-Dist: pandas>=2.0.3
Requires-Dist: pint
Requires-Dist: plotly
Requires-Dist: pvmismatch
Requires-Dist: pyDOE2
Requires-Dist: pyproj
Requires-Dist: pysolar
Requires-Dist: python-dotenv
Requires-Dist: python-rapidjson
Requires-Dist: pytz
Requires-Dist: rainflow
Requires-Dist: requests
Requires-Dist: scikit-learn
Requires-Dist: scikit-optimize
Requires-Dist: scipy
Requires-Dist: shapely
Requires-Dist: setuptools
Requires-Dist: timezonefinder
Requires-Dist: urllib3
Requires-Dist: openpyxl
Requires-Dist: attrs
Requires-Dist: utm
Requires-Dist: hopp>=3.1.1
Requires-Dist: orbit-nrel>=1.1
Requires-Dist: openmdao[all]
Requires-Dist: ProFAST
Requires-Dist: CoolProp
Provides-Extra: develop
Requires-Dist: pre-commit; extra == "develop"
Requires-Dist: isort; extra == "develop"
Requires-Dist: ruff; extra == "develop"
Requires-Dist: pytest; extra == "develop"
Requires-Dist: pytest-subtests; extra == "develop"
Requires-Dist: responses; extra == "develop"
Requires-Dist: Plotly; extra == "develop"
Requires-Dist: jupyter-book; extra == "develop"
Requires-Dist: sphinxcontrib-napoleon; extra == "develop"
Provides-Extra: examples
Requires-Dist: jupyterlab; extra == "examples"
Provides-Extra: all
Requires-Dist: greenheart[develop,examples]; extra == "all"
